os_apply_config/__init__.py
os_apply_config/apply_config.py
os_apply_config/collect_config.py
os_apply_config/config_exception.py
os_apply_config/oac_file.py
os_apply_config/renderers.py
os_apply_config/value_types.py
os_apply_config/version.py
os_apply_config/tests/__init__.py
os_apply_config/tests/test_apply_config.py
os_apply_config/tests/test_collect_config.py
os_apply_config/tests/test_json_renderer.py
os_apply_config/tests/test_oac_file.py
os_apply_config/tests/test_value_type.py
os_apply_config/tests/chown_templates/group.gid
os_apply_config/tests/chown_templates/group.gid.oac
os_apply_config/tests/chown_templates/group.name
os_apply_config/tests/chown_templates/group.name.oac
os_apply_config/tests/chown_templates/owner.name
os_apply_config/tests/chown_templates/owner.name.oac
os_apply_config/tests/chown_templates/owner.uid
os_apply_config/tests/chown_templates/owner.uid.oac
os_apply_config/tests/templates/etc/control/allow_empty
os_apply_config/tests/templates/etc/control/allow_empty.oac
os_apply_config/tests/templates/etc/control/empty
os_apply_config/tests/templates/etc/control/empty.oac
os_apply_config/tests/templates/etc/control/mode
os_apply_config/tests/templates/etc/control/mode.oac
os_apply_config/tests/templates/etc/glance/script.conf
os_apply_config/tests/templates/etc/keystone/keystone.conf
os_apply_config-14.0.1.dist-info/AUTHORS
os_apply_config-14.0.1.dist-info/LICENSE
os_apply_config-14.0.1.dist-info/METADATA
os_apply_config-14.0.1.dist-info/WHEEL
os_apply_config-14.0.1.dist-info/entry_points.txt
os_apply_config-14.0.1.dist-info/pbr.json
os_apply_config-14.0.1.dist-info/top_level.txt
os_apply_config-14.0.1.dist-info/RECORD
