Metadata-Version: 2.1
Name: os-apply-config
Version: 14.0.1
Summary: Config files from cloud metadata
Home-page: https://opendev.org/openstack/os-apply-config
Author: OpenStack
Author-email: openstack-discuss@lists.openstack.org
Classifier: Development Status :: 4 - Beta
Classifier: Environment :: Console
Classifier: Environment :: OpenStack
Classifier: Intended Audience :: Developers
Classifier: Intended Audience :: Information Technology
Classifier: License :: OSI Approved :: Apache Software License
Classifier: Operating System :: OS Independent
Classifier: Programming Language :: Python
Classifier: Programming Language :: Python :: 3
Classifier: Programming Language :: Python :: 3 :: Only
Classifier: Programming Language :: Python :: 3.8
Classifier: Programming Language :: Python :: 3.9
Classifier: Programming Language :: Python :: 3.10
Classifier: Programming Language :: Python :: 3.11
Classifier: Programming Language :: Python :: 3.12
Requires-Python: >=3.8
License-File: LICENSE
License-File: AUTHORS
Requires-Dist: pbr >=2.0.0
Requires-Dist: pystache >=0.5.4
Requires-Dist: PyYAML >=3.12
